app/__init__.py
app/dosya/__init__.py
app/dosya/depremler.py
app/dosya/tarih.py
app/internet/__init__.py
app/internet/baglanti.py
son_depremler_afad_api-1.1.2.dist-info/licenses/LICENCE
son_depremler_afad_api-1.1.2.dist-info/METADATA
son_depremler_afad_api-1.1.2.dist-info/WHEEL
son_depremler_afad_api-1.1.2.dist-info/top_level.txt
son_depremler_afad_api-1.1.2.dist-info/RECORD
