Metadata-Version: 2.4
Name: son-depremler-afad-api
Version: 1.1.2
Summary: AFAD'ın resmi web sayfasından son 24 saatte Türkiye'de olan depremleri çeken API
Home-page: https://github.com/umut-d/son-depremler-afad-api
Author: Umut D.
License: MIT
Classifier: License :: OSI Approved :: MIT License
Classifier: Programming Language :: Python :: 3
Classifier: Operating System :: OS Independent
Requires-Python: >=3
License-File: LICENCE
Provides-Extra: dev
Requires-Dist: twine>=4.0.2; extra == "dev"
Dynamic: author
Dynamic: classifier
Dynamic: description
Dynamic: description-content-type
Dynamic: home-page
Dynamic: license
Dynamic: license-file
Dynamic: provides-extra
Dynamic: requires-python
Dynamic: summary
